assister/__init__.py
assister/__main__.py
assister/base_models.py
assister/todo.csv
assister/api_requester/__init__.py
assister/api_requester/api_router.py
assister/api_requester/api_service.py
assister/dir_builder/__init__.py
assister/dir_builder/dir_router.py
assister/dir_builder/dir_service.py
assister/todos/__init__.py
assister/todos/models.py
assister/todos/todo_router.py
assister/todos/todo_service.py
assister-1.0.4.dist-info/METADATA
assister-1.0.4.dist-info/WHEEL
assister-1.0.4.dist-info/entry_points.txt
assister-1.0.4.dist-info/top_level.txt
assister-1.0.4.dist-info/RECORD
