Metadata-Version: 2.1
Name: assister
Version: 1.0.4
Summary: Simple Assister CLI, https://github.com/connormullett/assister
Home-page: https://github.com/connormullett/assister
Author: Connor Mullett
Author-email: UNKNOWN
License: MIT
Platform: UNKNOWN
